pipsqlite2addV3/__init__.py
pipsqlite2addV3-1.1.0.dist-info/METADATA
pipsqlite2addV3-1.1.0.dist-info/WHEEL
pipsqlite2addV3-1.1.0.dist-info/top_level.txt
pipsqlite2addV3-1.1.0.dist-info/RECORD
