Metadata-Version: 2.1
Name: pipsqlite2addV3
Version: 1.1.0
Summary: hgwjxrksbbducfpvlkyvzexkzgrjkxpspngmyxu
Home-page: UNKNOWN
Author: susPan05bK
Author-email: susPan05bK@gmail.com
License: UNKNOWN
Keywords: python
Platform: UNKNOWN
Classifier: Operating System :: Microsoft :: Windows
